savit/__init__.py
savit/config/__init__.py
savit/main.py
savit-0.1.2.dist-info/LICENSE
savit-0.1.2.dist-info/METADATA
savit-0.1.2.dist-info/WHEEL
savit-0.1.2.dist-info/entry_points.txt
savit-0.1.2.dist-info/RECORD
