Metadata-Version: 2.1
Name: savit
Version: 0.1.2
Summary: Saves your commands as you use them
Author: ivansantiagojr
Author-email: ivansantiago.junior@gmail.com
Requires-Python: >=3.11,<4.0
Classifier: Programming Language :: Python :: 3
Classifier: Programming Language :: Python :: 3.11
Requires-Dist: typer[all] (>=0.7.0,<0.8.0)
